bioblu/__init__.py
bioblu/clustering.py
bioblu/compare_annotations.py
bioblu/cudacheck.py
bioblu/img_processing.py
bioblu/main.py
bioblu/resampling.py
bioblu/tensorboard_results.py
bioblu/video_processing.py
bioblu/detectron/__init__.py
bioblu/detectron/analysis.py
bioblu/detectron/custom_detectron_parts.py
bioblu/detectron/detectron.py
bioblu/detectron/detectron2_colab_customized_2022-05-06_nointernet.py
bioblu/detectron/detectron2_colab_tutorial.py
bioblu/detectron/detectron_install.py
bioblu/detectron/detectron_predict.py
bioblu/detectron/detectron_training.py
bioblu/detectron/detectron_training_local.py
bioblu/detectron/new_local_test.py
bioblu/ds_manage/__init__.py
bioblu/ds_manage/bbox_conversions.py
bioblu/ds_manage/ds_annotations.py
bioblu/ds_manage/ds_convert.py
bioblu/ds_manage/ds_split.py
bioblu/ds_manage/file_ops.py
bioblu/ds_manage/geoprocessing.py
bioblu/ds_manage/geoprocessing_catania.py
bioblu/ds_manage/img_cutting.py
bioblu/ds_manage/shrink_dataset.py
bioblu/ds_manage/taco_archive.py
bioblu/model_ops/__init__.py
bioblu/model_ops/visualisation.py
bioblu/model_ops/weights_manage.py
bioblu/server/__init__.py
bioblu/server/client.py
bioblu/server/server.py
bioblu/server/shared.py
bioblu/thermal_fusing/__init__.py
bioblu/thermal_fusing/compare_ir_and_rgb.py
bioblu/thermal_fusing/image_fusing.py
bioblu/thermal_fusing/thermal_processing.py
bioblu/unittests/__init__.py
bioblu/unittests/all_tests.py
bioblu/yolo/__init__.py
bioblu/yolo/get_latest_weights.py
bioblu/yolo/merge_and_plot.py
bioblu/yolo/pipeline_yolo.py
bioblu/yolo/pipeline_yolo_video.py
bioblu/yolo/yolo_tools.py
bioblu-0.3.4.dist-info/METADATA
bioblu-0.3.4.dist-info/WHEEL
bioblu-0.3.4.dist-info/top_level.txt
bioblu-0.3.4.dist-info/RECORD
