Metadata-Version: 2.1
Name: bioblu
Version: 0.3.4
Summary: !!! PACKAGE IS IN DEVELOPMENT !!! Contains scripts used within the scope of the BIOBLU project. No warranty or guaranteed functionality.
Home-page: https://dsrg-ict.research.um.edu.mt/gianluca/bioblu
Author: Roland Pfeiffer
Author-email: 
Requires-Dist: ExifRead
Requires-Dist: Pillow
Requires-Dist: matplotlib
Requires-Dist: natsort
Requires-Dist: numpy
Requires-Dist: opencv-python
Requires-Dist: pandas
Requires-Dist: piexif
Requires-Dist: pyexiv2
Requires-Dist: scikit-learn
Requires-Dist: seaborn
Requires-Dist: setuptools
Requires-Dist: tensorflow
Requires-Dist: termcolor
Requires-Dist: torch
Requires-Dist: torchvision
